electrumsv-server/README.rst
electrumsv-server/__init__.py
electrumsv-server/requirements-dev.txt
electrumsv-server/requirements.txt
electrumsv-server/run.bat
electrumsv-server/electrumsv_server/__init__.py
electrumsv-server/electrumsv_server/__main__.py
electrumsv-server/electrumsv_server/application.py
electrumsv-server/electrumsv_server/config.py
electrumsv-server/electrumsv_server/constants.py
electrumsv-server/electrumsv_server/database.py
electrumsv-server/electrumsv_server/exceptions.py
electrumsv-server/electrumsv_server/payment_requests.py
electrumsv-server/electrumsv_server/txstatewebsocket.py
electrumsv-server/electrumsv_server/types.py
electrumsv_sdk/__init__.py
electrumsv_sdk/__main__.py
electrumsv_sdk/app_state.py
electrumsv_sdk/app_versions.py
electrumsv_sdk/argparsing.py
electrumsv_sdk/commands.py
electrumsv_sdk/components.py
electrumsv_sdk/config.py
electrumsv_sdk/constants.py
electrumsv_sdk/controller.py
electrumsv_sdk/exceptions.py
electrumsv_sdk/plugin_tools.py
electrumsv_sdk/sdk_types.py
electrumsv_sdk/utils.py
electrumsv_sdk/validate_cli_args.py
electrumsv_sdk/builtin_components/__init__.py
electrumsv_sdk/builtin_components/_common/__init__.py
electrumsv_sdk/builtin_components/_common/utils.py
electrumsv_sdk/builtin_components/_postgres/__init__.py
electrumsv_sdk/builtin_components/_postgres/postgres.py
electrumsv_sdk/builtin_components/dpp_proxy/__init__.py
electrumsv_sdk/builtin_components/dpp_proxy/dpp_proxy.py
electrumsv_sdk/builtin_components/dpp_proxy/install.py
electrumsv_sdk/builtin_components/dpp_proxy/exe-config/.env
electrumsv_sdk/builtin_components/electrumsv/__init__.py
electrumsv_sdk/builtin_components/electrumsv/electrumsv.py
electrumsv_sdk/builtin_components/electrumsv/local_tools.py
electrumsv_sdk/builtin_components/electrumsv_server/__init__.py
electrumsv_sdk/builtin_components/electrumsv_server/electrumsv_server.py
electrumsv_sdk/builtin_components/electrumsv_server/local_tools.py
electrumsv_sdk-0.0.50.dist-info/LICENCE
electrumsv_sdk-0.0.50.dist-info/METADATA
electrumsv_sdk-0.0.50.dist-info/WHEEL
electrumsv_sdk-0.0.50.dist-info/entry_points.txt
electrumsv_sdk-0.0.50.dist-info/top_level.txt
electrumsv_sdk-0.0.50.dist-info/RECORD
