Metadata-Version: 2.1
Name: electrumsv-sdk
Version: 0.0.50
Summary: ElectrumSV SDK
Home-page: https://github.com/electrumsv/electrumsv-sdk
Download-URL: https://github.com/electrumsv/electrumsv-sdk/tarball/0.0.50
Author: Roger Taylor
Author-email: roger.taylor.email@gmail.com
Maintainer: Roger Taylor
Maintainer-email: roger.taylor.email@gmail.com
License: Open BSV
Keywords: bitcoinsv,bsv,bitcoin sv,cryptocurrency,tools,wallet
Classifier: Development Status :: 4 - Beta
Classifier: Intended Audience :: Developers
Classifier: Intended Audience :: End Users/Desktop
Classifier: Natural Language :: English
Classifier: Operating System :: POSIX :: Linux
Classifier: Operating System :: MacOS :: MacOS X
Classifier: Operating System :: Microsoft :: Windows :: Windows 10
Classifier: Programming Language :: Python :: 3.10
Classifier: Programming Language :: Python :: Implementation :: CPython
License-File: LICENCE
Requires-Dist: electrumsv-node (>=0.0.25)
Requires-Dist: requests
Requires-Dist: filelock (>=3.3.2)
Requires-Dist: psutil-wheels (>=5.6.6)
Requires-Dist: setuptools (>=49.6.0)
Requires-Dist: aiorpcX (>=0.22.1)
Requires-Dist: bitcoinX (>=0.2.4)
Requires-Dist: peewee (>=3.13.3)
Requires-Dist: wheel
Requires-Dist: aiohttp (>=3.7.3)
Requires-Dist: tailer
Requires-Dist: stringcase
Requires-Dist: colorama
Requires-Dist: python-dotenv
Requires-Dist: asyncpg
Requires-Dist: pylru
Requires-Dist: pytest
Requires-Dist: aiodns
Requires-Dist: pysqlite3-binary ; platform_system == "Linux"
